countfiles/__init__.py
countfiles/cli.py
countfiles/node.py
countfiles2-0.5.2.dist-info/LICENSE
countfiles2-0.5.2.dist-info/METADATA
countfiles2-0.5.2.dist-info/WHEEL
countfiles2-0.5.2.dist-info/entry_points.txt
countfiles2-0.5.2.dist-info/top_level.txt
countfiles2-0.5.2.dist-info/RECORD
