Metadata-Version: 2.2
Name: countfiles2
Version: 0.5.2
Summary: Recursively count files per directory.
Author-email: Robert Huselius <robert@huseli.us>
Project-URL: Homepage, https://github.com/Eboreg/countfiles
Project-URL: Repository, https://github.com/Eboreg/countfiles.git
Classifier: Development Status :: 4 - Beta
Classifier: Environment :: Console
Classifier: License :: OSI Approved :: GNU General Public License v3 (GPLv3)
Requires-Python: >=3.7
License-File: LICENSE
Requires-Dist: colorama>=0.4.4
Provides-Extra: dev
Requires-Dist: isort; extra == "dev"
Requires-Dist: pylint; extra == "dev"
